toki/__init__.py
toki/openrouter.py
toki/openrouter_models.py
toki/openrouter_utils.py
toki/py.typed
toki/statemachine.py
toki-0.2.8.dist-info/METADATA
toki-0.2.8.dist-info/WHEEL
toki-0.2.8.dist-info/entry_points.txt
toki-0.2.8.dist-info/RECORD
