Metadata-Version: 2.4
Name: toki
Version: 0.2.8
Summary: Minimal universal LLM interface API
Project-URL: Repository, https://github.com/jataware/toki
Author-email: David Samson <david@jataware.com>
Requires-Python: >=3.10
Requires-Dist: requests>=2.32.5
Requires-Dist: typing-extensions>=4.15.0
